mlx/cli/core/__init__.py
mlx/cli/core/configure.py
mlx/cli/core/console.py
mlx/cli/core/extension.py
mlx/cli/core/main.py
mlx/cli/core/printer.py
mlx/cli/core/status.py
mlx/cli/core/util.py
ncloud_mlx-0.1.0.dist-info/METADATA
ncloud_mlx-0.1.0.dist-info/WHEEL
ncloud_mlx-0.1.0.dist-info/entry_points.txt
ncloud_mlx-0.1.0.dist-info/licenses/LICENSE
ncloud_mlx-0.1.0.dist-info/RECORD
