Metadata-Version: 2.4
Name: ncloud-mlx
Version: 0.1.0
Summary: CLI for the ML expert Platform on NAVER Cloud Platform
Project-URL: Homepage, https://guide.ncloud-docs.com/docs/ai-mlxp-overview
Project-URL: Documentation, https://guide.ncloud-docs.com/docs/ai-mlxp-overview
Author-email: navercloud-mlxp <dl_mlx_ncp_dev@navercorp.com>
License-Expression: Apache-2.0
License-File: LICENSE
Requires-Python: <4.0.0,>=3.9.0
Requires-Dist: aiofiles<24,>=23.2.1
Requires-Dist: httpx<0.28,>=0.27.0
Requires-Dist: ncloud-mlx-sdk>=0.1.1
Requires-Dist: pyfzf<0.4,>=0.3.1
Requires-Dist: python-dateutil<3,>=2.9.0.post0
Requires-Dist: pyyaml<7,>=6.0.1
Requires-Dist: rich<14,>=13.7.1
Requires-Dist: six<2,>=1.16.0
Requires-Dist: tabulate<0.10,>=0.9.0
Requires-Dist: timeago<2,>=1.0.16
Requires-Dist: typer==0.15.4
Requires-Dist: typing==3.7.4.3
Requires-Dist: yamlpath<4,>=3.8.2
Provides-Extra: all
Requires-Dist: ncloud-mlx-data-manager; extra == 'all'
Requires-Dist: ncloud-mlx-model-registry; extra == 'all'
Provides-Extra: data-manager
Requires-Dist: ncloud-mlx-data-manager; extra == 'data-manager'
Provides-Extra: model-registry
Requires-Dist: ncloud-mlx-model-registry; extra == 'model-registry'
